serial_data_handler_zxw/__init__.py
serial_data_handler_zxw/时间序列_数据处理.py
serial_data_handler_zxw/时间序列_数据对齐.py
serial_data_handler_zxw/金融K线_AI数据预处理.py
serial_data_handler_zxw-0.6.1.dist-info/METADATA
serial_data_handler_zxw-0.6.1.dist-info/WHEEL
serial_data_handler_zxw-0.6.1.dist-info/top_level.txt
serial_data_handler_zxw-0.6.1.dist-info/RECORD
