Metadata-Version: 2.1
Name: serial-data-handler-zxw
Version: 0.6.1
Summary: 人工智能_量化交易_金融数据预处理
Home-page: UNKNOWN
Author: xuewei zhang
Author-email: jingmu_predict@qq.com
License: UNKNOWN
Platform: UNKNOWN
Requires-Dist: pandas
Requires-Dist: numpy
Requires-Dist: tqdm
Requires-Dist: torch
